multinetx/__init__.py
multinetx-1.0.dev0.dist-info/METADATA
multinetx-1.0.dev0.dist-info/RECORD
multinetx-1.0.dev0.dist-info/WHEEL
multinetx-1.0.dev0.dist-info/entry_points.txt
multinetx-1.0.dev0.dist-info/top_level.txt
multinetx-1.0.dev0.dist-info/zip-safe
