Metadata-Version: 2.1
Name: multinetx
Version: 1.0.dev0
Summary: multiNetX is a python package for the manipulation and visualizatio
Home-page: https://github.com/nkoub/multinetx
Author: Nikos E Kouvaris
Author-email: nkouba@gmail.com
License: GPL3.0
Keywords: network networks graph graphs multilayer multilayers multiplex multigraphs
Platform: UNKNOWN
